Metadata-Version: 1.1
Name: tzwhere
Version: 3.0.3
Summary: Python library to look up timezone from lat / long offline
Home-page: https://github.com/pegler/pytzwhere
Author: Christoph Stich
Author-email: christoph@stich.xyz
License: MIT License
Platform: UNKNOWN
Classifier: Intended Audience :: Developers
Classifier: License :: OSI Approved :: MIT License
Classifier: Operating System :: OS Independent
Classifier: Programming Language :: Python
Classifier: Programming Language :: Python :: 2
Classifier: Programming Language :: Python :: 3
Classifier: Topic :: Software Development :: Localization
